nameko_mongodb/__init__.py
nameko_mongodb/database.py
nameko_mongodb-1.1.1.dist-info/LICENSE
nameko_mongodb-1.1.1.dist-info/METADATA
nameko_mongodb-1.1.1.dist-info/WHEEL
nameko_mongodb-1.1.1.dist-info/top_level.txt
nameko_mongodb-1.1.1.dist-info/zip-safe
nameko_mongodb-1.1.1.dist-info/RECORD
