Metadata-Version: 2.1
Name: nameko-mongodb
Version: 1.1.1
Summary: Simple MongoDb dependency for nameko (microservices framework). Based on https://github.com/saiqi/nameko-mongodb
Home-page: https://github.com/alexshin/nameko-mongodb
Author: Alex Shinkevich
Author-email: alex.shinkevich@gmail.com
License: Apache License, Version 2.0
Platform: UNKNOWN
Classifier: Programming Language :: Python
Classifier: Programming Language :: Python :: 2.7
Classifier: Programming Language :: Python :: 3
Classifier: Programming Language :: Python :: 3.4
Classifier: Programming Language :: Python :: 3.5
Classifier: Programming Language :: Python :: 3.6
Classifier: Programming Language :: Python :: 3.7
Classifier: Topic :: Internet
Classifier: Topic :: Software Development :: Libraries :: Python Modules
Classifier: Intended Audience :: Developers
Requires-Dist: nameko (>=2.11.0)
Requires-Dist: pymongo
